{
  "schemaVersion": 1,
  "configProperties": {
    "name": "default"
  },
  "categories": [],
  "wrappers": [
    {
      "id": "default",
      "position": 0
    }
  ],
  "apps": [
    {
      "id": "4afbe541-79e7-48be-994a-10bd0bc2edd0",
      "name": "Calibre",
      "url": "https://books.virtual.lontiotlabs.au",
      "appearance": {
        "iconUrl": "https://cdn.jsdelivr.net/gh/walkxcode/dashboard-icons/svg/calibre-web.svg",
        "appNameStatus": "normal",
        "positionAppName": "column",
        "lineClampAppName": 1,
        "appNameFontSize": 16
      },
      "network": {
        "enabledStatusChecker": true,
        "statusCodes": [
          "200",
          "301",
          "302",
          "304",
          "307",
          "308"
        ]
      },
      "behaviour": {
        "isOpeningNewTab": true,
        "externalUrl": "https://books.virtual.lontiotlabs.au"
      },
      "area": {
        "type": "wrapper",
        "properties": {
          "id": "default"
        }
      },
      "shape": {
        "lg": {
          "location": {
            "x": 5,
            "y": 1
          },
          "size": {
            "width": 1,
            "height": 1
          }
        }
      },
      "integration": {
        "type": null,
        "properties": []
      }
    },
    {
      "id": "f5b16bc3-3001-4549-843a-d6e4e69513b9",
      "name": "Navidrome",
      "url": "https://music.lontiotlabs.au",
      "appearance": {
        "iconUrl": "https://cdn.jsdelivr.net/gh/walkxcode/dashboard-icons/svg/navidrome-light.svg",
        "appNameStatus": "normal",
        "positionAppName": "column",
        "lineClampAppName": 1,
        "appNameFontSize": 16
      },
      "network": {
        "enabledStatusChecker": true,
        "statusCodes": [
          "200",
          "301",
          "302",
          "304",
          "307",
          "308"
        ]
      },
      "behaviour": {
        "isOpeningNewTab": true,
        "externalUrl": "https://music.lontiotlabs.au"
      },
      "area": {
        "type": "wrapper",
        "properties": {
          "id": "default"
        }
      },
      "shape": {
        "lg": {
          "location": {
            "x": 6,
            "y": 2
          },
          "size": {
            "width": 1,
            "height": 1
          }
        }
      },
      "integration": {
        "type": null,
        "properties": []
      }
    },
    {
      "id": "89e473de-3583-4933-a23c-400a8b7de1d9",
      "name": "Notes",
      "url": "https://notes.virtual.lontiotlabs.au/",
      "appearance": {
        "iconUrl": "https://play-lh.googleusercontent.com/0WzNnQJyEuOyvkZvYVpGkQJEvOfEF9kBnbLnLQioqUAX_DlV6wP8hyH8BgVBHQa1V9A=w240-h480-rw",
        "appNameStatus": "normal",
        "positionAppName": "column",
        "lineClampAppName": 1,
        "appNameFontSize": 16
      },
      "network": {
        "enabledStatusChecker": true,
        "statusCodes": [
          "200",
          "301",
          "302",
          "304",
          "307",
          "308"
        ]
      },
      "behaviour": {
        "isOpeningNewTab": true,
        "externalUrl": "https://notes.virtual.lontiotlabs.au/"
      },
      "area": {
        "type": "wrapper",
        "properties": {
          "id": "default"
        }
      },
      "shape": {
        "lg": {
          "location": {
            "x": 6,
            "y": 1
          },
          "size": {
            "width": 1,
            "height": 1
          }
        },
        "md": {
          "location": {
            "x": 3,
            "y": 4
          },
          "size": {
            "width": 1,
            "height": 1
          }
        }
      },
      "integration": {
        "type": null,
        "properties": []
      }
    },
    {
      "id": "1dd8ea9d-ab99-49df-bb65-9529b0a803e3",
      "name": "Prime",
      "url": "https://www.primevideo.com/",
      "appearance": {
        "iconUrl": "https://cdn.jsdelivr.net/gh/PapirusDevelopmentTeam/papirus_icons/src/apps_amazon_prime_video.svg",
        "appNameStatus": "normal",
        "positionAppName": "column",
        "lineClampAppName": 1,
        "appNameFontSize": 16
      },
      "network": {
        "enabledStatusChecker": true,
        "statusCodes": [
          "200"
        ]
      },
      "behaviour": {
        "isOpeningNewTab": true,
        "externalUrl": "https://www.primevideo.com/"
      },
      "area": {
        "type": "wrapper",
        "properties": {
          "id": "default"
        }
      },
      "shape": {
        "lg": {
          "location": {
            "x": 7,
            "y": 2
          },
          "size": {
            "width": 1,
            "height": 1
          }
        },
        "md": {
          "location": {
            "x": 3,
            "y": 5
          },
          "size": {
            "width": 1,
            "height": 1
          }
        }
      },
      "integration": {
        "type": null,
        "properties": []
      }
    },
    {
      "id": "10eafeef-d1c9-4731-8b49-bdd43c9713a1",
      "name": "Traefik-int",
      "url": "https://traefik.virtual.lontiotlabs.au/dashboard/#",
      "appearance": {
        "iconUrl": "https://cdn.jsdelivr.net/gh/walkxcode/dashboard-icons/png/traefik.png",
        "appNameStatus": "normal",
        "positionAppName": "column",
        "lineClampAppName": 1,
        "appNameFontSize": 16
      },
      "network": {
        "enabledStatusChecker": true,
        "statusCodes": [
          "200"
        ]
      },
      "behaviour": {
        "isOpeningNewTab": true,
        "externalUrl": "https://traefik.virtual.lontiotlabs.au/dashboard/#/"
      },
      "area": {
        "type": "wrapper",
        "properties": {
          "id": "default"
        }
      },
      "shape": {
        "lg": {
          "location": {
            "x": 10,
            "y": 3
          },
          "size": {
            "width": 1,
            "height": 1
          }
        },
        "md": {
          "location": {
            "x": 0,
            "y": 3
          },
          "size": {
            "width": 1,
            "height": 1
          }
        }
      },
      "integration": {
        "type": null,
        "properties": []
      }
    },
    {
      "id": "1bbcf73d-fd82-49e7-ab85-4f6e614649ae",
      "name": "Traefik-ext",
      "url": "https://traefik.lontiotlabs.au/dashboard/#",
      "appearance": {
        "iconUrl": "https://cdn.jsdelivr.net/gh/walkxcode/dashboard-icons/png/traefik.png",
        "appNameStatus": "normal",
        "appNameFontSize": 16,
        "positionAppName": "column",
        "lineClampAppName": 1
      },
      "network": {
        "enabledStatusChecker": true,
        "statusCodes": [
          "200",
          "301",
          "302",
          "304",
          "307",
          "308"
        ]
      },
      "behaviour": {
        "isOpeningNewTab": true,
        "externalUrl": "https://traefik.lontiotlabs.au/dashboard/#/"
      },
      "area": {
        "type": "wrapper",
        "properties": {
          "id": "default"
        }
      },
      "shape": {
        "lg": {
          "location": {
            "x": 11,
            "y": 3
          },
          "size": {
            "width": 1,
            "height": 1
          }
        },
        "md": {
          "location": {
            "x": 1,
            "y": 3
          },
          "size": {
            "width": 1,
            "height": 1
          }
        }
      },
      "integration": {
        "type": null,
        "properties": []
      }
    },
    {
      "id": "da845ee6-ebfb-4205-ad11-89d808141978",
      "name": "Tablet",
      "url": "https://tablet.iot.lontiotlabs.au",
      "appearance": {
        "iconUrl": "https://play-lh.googleusercontent.com/1PCzLvQR-NVM3iZOKwdukbn495S11wenLr0P1FB31Igr50zgQeTyMDhFAJh1yKuM",
        "appNameStatus": "normal",
        "positionAppName": "column",
        "lineClampAppName": 1,
        "appNameFontSize": 16
      },
      "network": {
        "enabledStatusChecker": true,
        "statusCodes": [
          "200",
          "301",
          "302",
          "304",
          "307",
          "308"
        ]
      },
      "behaviour": {
        "isOpeningNewTab": true,
        "externalUrl": "https://tablet.iot.lontiotlabs.au/"
      },
      "area": {
        "type": "wrapper",
        "properties": {
          "id": "default"
        }
      },
      "shape": {
        "lg": {
          "location": {
            "x": 10,
            "y": 4
          },
          "size": {
            "width": 1,
            "height": 1
          }
        },
        "md": {
          "location": {
            "x": 0,
            "y": 4
          },
          "size": {
            "width": 1,
            "height": 1
          }
        }
      },
      "integration": {
        "type": null,
        "properties": []
      }
    },
    {
      "id": "2ec7de36-a43d-48a8-803c-7f8f19010ec2",
      "name": "Ebay",
      "url": "https://www.ebay.com.au/",
      "appearance": {
        "iconUrl": "https://cdn.jsdelivr.net/gh/walkxcode/dashboard-icons/png/ebay.png",
        "appNameStatus": "normal",
        "positionAppName": "column",
        "lineClampAppName": 1,
        "appNameFontSize": 16
      },
      "network": {
        "enabledStatusChecker": true,
        "statusCodes": [
          "200"
        ]
      },
      "behaviour": {
        "isOpeningNewTab": true,
        "externalUrl": "https://www.ebay.com.au/"
      },
      "area": {
        "type": "wrapper",
        "properties": {
          "id": "default"
        }
      },
      "shape": {
        "lg": {
          "location": {
            "x": 4,
            "y": 6
          },
          "size": {
            "width": 1,
            "height": 1
          }
        },
        "md": {
          "location": {
            "x": 5,
            "y": 1
          },
          "size": {
            "width": 1,
            "height": 1
          }
        }
      },
      "integration": {
        "type": null,
        "properties": []
      }
    },
    {
      "id": "66bffbd4-6528-46f9-adfd-9d659b4c00c0",
      "name": "Audiobook",
      "url": "https://audiobook.lontiotlabs.au",
      "appearance": {
        "iconUrl": "https://cdn.jsdelivr.net/gh/walkxcode/dashboard-icons/svg/audiobookshelf.svg",
        "appNameStatus": "normal",
        "positionAppName": "column",
        "lineClampAppName": 1,
        "appNameFontSize": 16
      },
      "network": {
        "enabledStatusChecker": true,
        "statusCodes": [
          "200",
          "301",
          "302",
          "304",
          "307",
          "308"
        ]
      },
      "behaviour": {
        "isOpeningNewTab": true,
        "externalUrl": "https://audiobook.lontiotlabs.au"
      },
      "area": {
        "type": "wrapper",
        "properties": {
          "id": "default"
        }
      },
      "shape": {
        "lg": {
          "location": {
            "x": 11,
            "y": 4
          },
          "size": {
            "width": 1,
            "height": 1
          }
        }
      },
      "integration": {
        "type": null,
        "properties": []
      }
    },
    {
      "id": "a02b02a6-d0e4-4dfe-ac36-37a249c55d3c",
      "name": "Gumtree",
      "url": "https://www.gumtree.com.au/",
      "appearance": {
        "iconUrl": "https://play-lh.googleusercontent.com/Bhe5NnjQSoGqcCvLqg9BUNsRlL6o3uGwlOpe-FAdxAot1qeurbHb__RbxVCioYF2XFQl",
        "appNameStatus": "normal",
        "positionAppName": "column",
        "lineClampAppName": 1,
        "appNameFontSize": 16
      },
      "network": {
        "enabledStatusChecker": true,
        "statusCodes": [
          "200"
        ]
      },
      "behaviour": {
        "isOpeningNewTab": true,
        "externalUrl": "https://www.gumtree.com.au/"
      },
      "area": {
        "type": "wrapper",
        "properties": {
          "id": "default"
        }
      },
      "shape": {
        "lg": {
          "location": {
            "x": 5,
            "y": 5
          },
          "size": {
            "width": 1,
            "height": 1
          }
        },
        "md": {
          "location": {
            "x": 5,
            "y": 0
          },
          "size": {
            "width": 1,
            "height": 1
          }
        }
      },
      "integration": {
        "type": null,
        "properties": []
      }
    },
    {
      "id": "787a9b3f-290b-4d0a-9ba2-372358658216",
      "name": "Digikey",
      "url": "https://www.digikey.com.au/",
      "appearance": {
        "iconUrl": "https://www.digikey.com/htmldatasheets/production/HTMLTemplate/images/logo_dk.png",
        "appNameStatus": "normal",
        "positionAppName": "column",
        "lineClampAppName": 1,
        "appNameFontSize": 16
      },
      "network": {
        "enabledStatusChecker": true,
        "statusCodes": [
          "200"
        ]
      },
      "behaviour": {
        "isOpeningNewTab": true,
        "externalUrl": "https://www.digikey.com.au/"
      },
      "area": {
        "type": "wrapper",
        "properties": {
          "id": "default"
        }
      },
      "shape": {
        "lg": {
          "location": {
            "x": 6,
            "y": 5
          },
          "size": {
            "width": 1,
            "height": 1
          }
        },
        "md": {
          "location": {
            "x": 1,
            "y": 3
          },
          "size": {
            "width": 1,
            "height": 1
          }
        }
      },
      "integration": {
        "type": null,
        "properties": []
      }
    },
    {
      "id": "52f696db-b9cc-487a-8863-47f1bb28511b",
      "name": "Mouser",
      "url": "https://au.mouser.com/",
      "appearance": {
        "iconUrl": "https://e7.pngegg.com/pngimages/805/550/png-clipart-logo-mouser-electronics-computer-icons-ohms-logo-blue-electronics.png",
        "appNameStatus": "normal",
        "positionAppName": "column",
        "lineClampAppName": 1,
        "appNameFontSize": 16
      },
      "network": {
        "enabledStatusChecker": true,
        "statusCodes": [
          "200"
        ]
      },
      "behaviour": {
        "isOpeningNewTab": true,
        "externalUrl": "https://au.mouser.com/"
      },
      "area": {
        "type": "wrapper",
        "properties": {
          "id": "default"
        }
      },
      "shape": {
        "lg": {
          "location": {
            "x": 7,
            "y": 5
          },
          "size": {
            "width": 1,
            "height": 1
          }
        },
        "md": {
          "location": {
            "x": 1,
            "y": 0
          },
          "size": {
            "width": 1,
            "height": 1
          }
        }
      },
      "integration": {
        "type": null,
        "properties": []
      }
    },
    {
      "id": "73d019de-0a99-4be8-8559-8873ee9ac642",
      "name": "Scorptec",
      "url": "https://www.scorptec.com.au",
      "appearance": {
        "iconUrl": "https://www.scorptec.com.au/assets/images/share-link-logo.png",
        "appNameStatus": "normal",
        "positionAppName": "column",
        "lineClampAppName": 1,
        "appNameFontSize": 16
      },
      "network": {
        "enabledStatusChecker": true,
        "statusCodes": [
          "200",
          "301",
          "302",
          "304",
          "307",
          "308"
        ]
      },
      "behaviour": {
        "isOpeningNewTab": true,
        "externalUrl": "https://www.scorptec.com.au/"
      },
      "area": {
        "type": "wrapper",
        "properties": {
          "id": "default"
        }
      },
      "shape": {
        "lg": {
          "location": {
            "x": 8,
            "y": 5
          },
          "size": {
            "width": 1,
            "height": 1
          }
        },
        "md": {
          "location": {
            "x": 2,
            "y": 1
          },
          "size": {
            "width": 1,
            "height": 1
          }
        }
      },
      "integration": {
        "type": null,
        "properties": []
      }
    },
    {
      "id": "64b1f995-88b6-4b90-90a2-571401b3dab3",
      "name": "PCCG",
      "url": "https://www.pccasegear.com",
      "appearance": {
        "iconUrl": "https://files.pccasegear.com/images/1626237441-LOGOStyled1000x1000.jpg",
        "appNameStatus": "normal",
        "positionAppName": "column",
        "lineClampAppName": 1,
        "appNameFontSize": 16
      },
      "network": {
        "enabledStatusChecker": true,
        "statusCodes": [
          "200",
          "301",
          "302",
          "304",
          "307",
          "308"
        ]
      },
      "behaviour": {
        "isOpeningNewTab": true,
        "externalUrl": "https://www.pccasegear.com/"
      },
      "area": {
        "type": "wrapper",
        "properties": {
          "id": "default"
        }
      },
      "shape": {
        "lg": {
          "location": {
            "x": 9,
            "y": 5
          },
          "size": {
            "width": 1,
            "height": 1
          }
        },
        "md": {
          "location": {
            "x": 0,
            "y": 2
          },
          "size": {
            "width": 1,
            "height": 1
          }
        }
      },
      "integration": {
        "type": null,
        "properties": []
      }
    },
    {
      "id": "01eaf438-f194-4a7c-8abe-60c569a967da",
      "name": "Cloudflare",
      "url": "https://www.cloudflare.com/en-au/",
      "appearance": {
        "iconUrl": "https://cdn-icons-png.flaticon.com/512/5969/5969044.png",
        "appNameStatus": "normal",
        "positionAppName": "column",
        "lineClampAppName": 1,
        "appNameFontSize": 16
      },
      "network": {
        "enabledStatusChecker": true,
        "statusCodes": [
          "200",
          "301",
          "302",
          "304",
          "307",
          "308"
        ]
      },
      "behaviour": {
        "isOpeningNewTab": true,
        "externalUrl": "https://www.cloudflare.com/en-au/"
      },
      "area": {
        "type": "wrapper",
        "properties": {
          "id": "default"
        }
      },
      "shape": {
        "lg": {
          "location": {
            "x": 10,
            "y": 5
          },
          "size": {
            "width": 1,
            "height": 1
          }
        },
        "md": {
          "location": {
            "x": 0,
            "y": 7
          },
          "size": {
            "width": 1,
            "height": 1
          }
        }
      },
      "integration": {
        "type": null,
        "properties": []
      }
    },
    {
      "id": "aa9fdfc4-5875-4c1c-869e-ed4029348620",
      "name": "Lora",
      "url": "https://rak.iot.lontiotlabs.au/cgi-bin/luci",
      "appearance": {
        "iconUrl": "https://hackster.imgix.net/uploads/attachments/670831/untitled_design_(1)_Owo51ooXAa.png?auto=compress%2Cformat",
        "appNameStatus": "normal",
        "positionAppName": "column",
        "lineClampAppName": 1,
        "appNameFontSize": 16
      },
      "network": {
        "enabledStatusChecker": true,
        "statusCodes": [
          "200",
          "301",
          "302",
          "304",
          "307",
          "308"
        ]
      },
      "behaviour": {
        "isOpeningNewTab": true,
        "externalUrl": "https://rak.iot.lontiotlabs.au/cgi-bin/luci"
      },
      "area": {
        "type": "wrapper",
        "properties": {
          "id": "default"
        }
      },
      "shape": {
        "lg": {
          "location": {
            "x": 11,
            "y": 5
          },
          "size": {
            "width": 1,
            "height": 1
          }
        },
        "md": {
          "location": {
            "x": 5,
            "y": 5
          },
          "size": {
            "width": 1,
            "height": 1
          }
        }
      },
      "integration": {
        "type": null,
        "properties": []
      }
    },
    {
      "id": "e7b83284-885f-449e-827d-87ac94e29018",
      "name": "Github",
      "url": "https://github.com/",
      "appearance": {
        "iconUrl": "https://cdn.jsdelivr.net/gh/walkxcode/dashboard-icons/png/github.png",
        "appNameStatus": "normal",
        "positionAppName": "column",
        "lineClampAppName": 1,
        "appNameFontSize": 16
      },
      "network": {
        "enabledStatusChecker": true,
        "statusCodes": [
          "200"
        ]
      },
      "behaviour": {
        "isOpeningNewTab": true,
        "externalUrl": "https://github.com/"
      },
      "area": {
        "type": "wrapper",
        "properties": {
          "id": "default"
        }
      },
      "shape": {
        "lg": {
          "location": {
            "x": 10,
            "y": 6
          },
          "size": {
            "width": 1,
            "height": 1
          }
        },
        "md": {
          "location": {
            "x": 5,
            "y": 6
          },
          "size": {
            "width": 1,
            "height": 1
          }
        }
      },
      "integration": {
        "type": null,
        "properties": []
      }
    },
    {
      "id": "9debb992-0fbb-46b3-b387-47282865e747",
      "name": "Milesight",
      "url": "https://milesight.iot.lontiotlabs.au/",
      "appearance": {
        "iconUrl": "https://play-lh.googleusercontent.com/hRl4JVfhjMWJmDGl3xfqZVXPEGlgqzKOJTauC3_9-WYtDaeRMcl_O56xTO9C7oV9FrJm=w240-h480-rw",
        "appNameStatus": "normal",
        "positionAppName": "column",
        "lineClampAppName": 1,
        "appNameFontSize": 16
      },
      "network": {
        "enabledStatusChecker": true,
        "statusCodes": [
          "200",
          "301",
          "302",
          "304",
          "307",
          "308"
        ]
      },
      "behaviour": {
        "isOpeningNewTab": true,
        "externalUrl": "https://milesight.iot.lontiotlabs.au/"
      },
      "area": {
        "type": "wrapper",
        "properties": {
          "id": "default"
        }
      },
      "shape": {
        "lg": {
          "location": {
            "x": 11,
            "y": 6
          },
          "size": {
            "width": 1,
            "height": 1
          }
        },
        "md": {
          "location": {
            "x": 0,
            "y": 6
          },
          "size": {
            "width": 1,
            "height": 1
          }
        }
      },
      "integration": {
        "type": null,
        "properties": []
      }
    },
    {
      "id": "423ad622-32ef-42ba-b1f7-59994e785684",
      "name": "Azure",
      "url": "https://ms.portal.azure.com/",
      "appearance": {
        "iconUrl": "https://cdn.jsdelivr.net/gh/walkxcode/dashboard-icons/png/azure.png",
        "appNameStatus": "normal",
        "positionAppName": "column",
        "lineClampAppName": 1,
        "appNameFontSize": 16
      },
      "network": {
        "enabledStatusChecker": true,
        "statusCodes": [
          "200"
        ]
      },
      "behaviour": {
        "isOpeningNewTab": true,
        "externalUrl": "https://ms.portal.azure.com/"
      },
      "area": {
        "type": "wrapper",
        "properties": {
          "id": "default"
        }
      },
      "shape": {
        "lg": {
          "location": {
            "x": 10,
            "y": 7
          },
          "size": {
            "width": 1,
            "height": 1
          }
        },
        "md": {
          "location": {
            "x": 2,
            "y": 6
          },
          "size": {
            "width": 1,
            "height": 1
          }
        }
      },
      "integration": {
        "type": null,
        "properties": []
      }
    },
    {
      "id": "af8660b2-28e3-455e-a63c-39dd8bf2103e",
      "name": "Particle",
      "url": "https://console.particle.io",
      "appearance": {
        "iconUrl": "https://www.electronicwings.com/storage/PlatformSection/TopicContent/352/description/particle-vertical.png",
        "appNameStatus": "normal",
        "positionAppName": "column",
        "lineClampAppName": 1,
        "appNameFontSize": 16
      },
      "network": {
        "enabledStatusChecker": true,
        "statusCodes": [
          "200",
          "301",
          "302",
          "304",
          "307",
          "308"
        ]
      },
      "behaviour": {
        "isOpeningNewTab": true,
        "externalUrl": "https://console.particle.io/"
      },
      "area": {
        "type": "wrapper",
        "properties": {
          "id": "default"
        }
      },
      "shape": {
        "lg": {
          "location": {
            "x": 11,
            "y": 7
          },
          "size": {
            "width": 1,
            "height": 1
          }
        },
        "md": {
          "location": {
            "x": 1,
            "y": 6
          },
          "size": {
            "width": 1,
            "height": 1
          }
        }
      },
      "integration": {
        "type": null,
        "properties": []
      }
    },
    {
      "id": "1be559f2-5f75-49cc-b4c9-901a7164cd54",
      "name": "EveryCircuit",
      "url": "https://everycircuit.com/app",
      "appearance": {
        "iconUrl": "https://play-lh.googleusercontent.com/dkRmvNZVKK3NJLiD3XcCst3ALA-fiTjfFCbkghWS5kFBbqC8D7X7sWb_QDjJEeUWIGI=w240-h480-rw",
        "appNameStatus": "normal",
        "positionAppName": "column",
        "lineClampAppName": 1,
        "appNameFontSize": 16
      },
      "network": {
        "enabledStatusChecker": true,
        "statusCodes": [
          "200",
          "301",
          "302",
          "304",
          "307",
          "308"
        ]
      },
      "behaviour": {
        "isOpeningNewTab": true,
        "externalUrl": "https://everycircuit.com/app/"
      },
      "area": {
        "type": "wrapper",
        "properties": {
          "id": "default"
        }
      },
      "shape": {
        "lg": {
          "location": {
            "x": 8,
            "y": 6
          },
          "size": {
            "width": 1,
            "height": 1
          }
        },
        "md": {
          "location": {
            "x": 4,
            "y": 5
          },
          "size": {
            "width": 1,
            "height": 1
          }
        }
      },
      "integration": {
        "type": null,
        "properties": []
      }
    },
    {
      "id": "4a0bcab9-1012-4147-a15e-04211fb3c974",
      "name": "Thingiverse",
      "url": "https://www.thingiverse.com",
      "appearance": {
        "iconUrl": "https://encrypted-tbn0.gstatic.com/images?q=tbn:ANd9GcQgU3afSazpMI5Om4eTYbIsfvHuvWPyRwuCog&s",
        "appNameStatus": "normal",
        "positionAppName": "column",
        "lineClampAppName": 1,
        "appNameFontSize": 16
      },
      "network": {
        "enabledStatusChecker": true,
        "statusCodes": [
          "200",
          "301",
          "302",
          "304",
          "307",
          "308"
        ]
      },
      "behaviour": {
        "isOpeningNewTab": true,
        "externalUrl": "https://www.thingiverse.com/"
      },
      "area": {
        "type": "wrapper",
        "properties": {
          "id": "default"
        }
      },
      "shape": {
        "lg": {
          "location": {
            "x": 8,
            "y": 7
          },
          "size": {
            "width": 1,
            "height": 1
          }
        },
        "md": {
          "location": {
            "x": 4,
            "y": 6
          },
          "size": {
            "width": 1,
            "height": 1
          }
        }
      },
      "integration": {
        "type": null,
        "properties": []
      }
    },
    {
      "id": "48ad4858-6c8e-4f06-b4a7-781d6ee69acb",
      "name": "Jaycar",
      "url": "https://www.jaycar.com.au/",
      "appearance": {
        "iconUrl": "https://upload.wikimedia.org/wikipedia/en/thumb/d/d5/Jaycar_Logo%2C_2019.svg/1200px-Jaycar_Logo%2C_2019.svg.png",
        "appNameStatus": "normal",
        "positionAppName": "column",
        "lineClampAppName": 1,
        "appNameFontSize": 16
      },
      "network": {
        "enabledStatusChecker": true,
        "statusCodes": [
          "200",
          "301",
          "302",
          "304",
          "307",
          "308"
        ]
      },
      "behaviour": {
        "isOpeningNewTab": true,
        "externalUrl": "https://www.jaycar.com.au/"
      },
      "area": {
        "type": "wrapper",
        "properties": {
          "id": "default"
        }
      },
      "shape": {
        "lg": {
          "location": {
            "x": 7,
            "y": 6
          },
          "size": {
            "width": 1,
            "height": 1
          }
        },
        "md": {
          "location": {
            "x": 0,
            "y": 0
          },
          "size": {
            "width": 1,
            "height": 1
          }
        }
      },
      "integration": {
        "type": null,
        "properties": []
      }
    },
    {
      "id": "d42db05b-b3f7-4ab3-8530-514f88ddd665",
      "name": "Iot",
      "url": "https://www.iot-store.com.au/",
      "appearance": {
        "iconUrl": "https://cdn-icons-png.flaticon.com/512/1185/1185915.png",
        "appNameStatus": "normal",
        "positionAppName": "column",
        "lineClampAppName": 1,
        "appNameFontSize": 16
      },
      "network": {
        "enabledStatusChecker": true,
        "statusCodes": [
          "200"
        ]
      },
      "behaviour": {
        "isOpeningNewTab": true,
        "externalUrl": "https://www.iot-store.com.au/"
      },
      "area": {
        "type": "wrapper",
        "properties": {
          "id": "default"
        }
      },
      "shape": {
        "lg": {
          "location": {
            "x": 6,
            "y": 6
          },
          "size": {
            "width": 1,
            "height": 1
          }
        },
        "md": {
          "location": {
            "x": 0,
            "y": 4
          },
          "size": {
            "width": 1,
            "height": 1
          }
        }
      },
      "integration": {
        "type": null,
        "properties": []
      }
    },
    {
      "id": "d949b633-391a-4563-9287-89c837a7b87f",
      "name": "RS Online",
      "url": "https://au.rs-online.com/web/",
      "appearance": {
        "iconUrl": "https://upload.wikimedia.org/wikipedia/commons/thumb/d/d9/RS_Components_Logo.svg/1200px-RS_Components_Logo.svg.png",
        "appNameStatus": "normal",
        "positionAppName": "column",
        "lineClampAppName": 1,
        "appNameFontSize": 16
      },
      "network": {
        "enabledStatusChecker": true,
        "statusCodes": [
          "200"
        ]
      },
      "behaviour": {
        "isOpeningNewTab": true,
        "externalUrl": "https://au.rs-online.com/web/"
      },
      "area": {
        "type": "wrapper",
        "properties": {
          "id": "default"
        }
      },
      "shape": {
        "lg": {
          "location": {
            "x": 5,
            "y": 6
          },
          "size": {
            "width": 1,
            "height": 1
          }
        },
        "md": {
          "location": {
            "x": 4,
            "y": 1
          },
          "size": {
            "width": 1,
            "height": 1
          }
        }
      },
      "integration": {
        "type": null,
        "properties": []
      }
    },
    {
      "id": "a617ea6a-3214-4fba-9742-4362110e9481",
      "name": "Plex",
      "url": "https://plex.lontiotlabs.au/web/index.html#!",
      "appearance": {
        "iconUrl": "https://cdn.jsdelivr.net/gh/walkxcode/dashboard-icons/png/plex.png",
        "appNameStatus": "normal",
        "positionAppName": "column",
        "lineClampAppName": 1,
        "appNameFontSize": 16
      },
      "network": {
        "enabledStatusChecker": true,
        "statusCodes": [
          "200"
        ]
      },
      "behaviour": {
        "isOpeningNewTab": true,
        "externalUrl": "https://plex.lontiotlabs.au/web/index.html#!/"
      },
      "area": {
        "type": "wrapper",
        "properties": {
          "id": "default"
        }
      },
      "shape": {
        "lg": {
          "location": {
            "x": 5,
            "y": 2
          },
          "size": {
            "width": 1,
            "height": 1
          }
        },
        "md": {
          "location": {
            "x": 2,
            "y": 3
          },
          "size": {
            "width": 1,
            "height": 1
          }
        }
      },
      "integration": {
        "type": "plex",
        "properties": [
          {
            "field": "apiKey",
            "type": "private",
            "value": "XVDwZYwx6ft6sbDiV4qG"
          }
        ]
      }
    },
    {
      "id": "15e32237-33eb-4109-a02a-94e7e8b21c2e",
      "name": "Speed Test",
      "url": "https://speed.virtual.lontiotlabs.au",
      "appearance": {
        "iconUrl": "https://cdn.jsdelivr.net/gh/walkxcode/dashboard-icons/png/librespeed.png",
        "appNameStatus": "normal",
        "positionAppName": "column",
        "lineClampAppName": 1,
        "appNameFontSize": 16
      },
      "network": {
        "enabledStatusChecker": true,
        "statusCodes": [
          "200"
        ]
      },
      "behaviour": {
        "isOpeningNewTab": true,
        "externalUrl": "https://speed.virtual.lontiotlabs.au"
      },
      "area": {
        "type": "wrapper",
        "properties": {
          "id": "default"
        }
      },
      "shape": {
        "lg": {
          "location": {
            "x": 10,
            "y": 1
          },
          "size": {
            "width": 1,
            "height": 1
          }
        },
        "md": {
          "location": {
            "x": 2,
            "y": 4
          },
          "size": {
            "width": 1,
            "height": 1
          }
        }
      },
      "integration": {
        "type": null,
        "properties": []
      }
    },
    {
      "id": "6532d86f-56fa-4afe-9e15-d0afc674a3eb",
      "name": "Bitwarden",
      "url": "https://vault.bitwarden.com/#/login",
      "appearance": {
        "iconUrl": "https://cdn.jsdelivr.net/gh/walkxcode/dashboard-icons/svg/bitwarden.svg",
        "appNameStatus": "normal",
        "positionAppName": "column",
        "lineClampAppName": 1,
        "appNameFontSize": 16
      },
      "network": {
        "enabledStatusChecker": true,
        "statusCodes": [
          "200",
          "301",
          "302",
          "304",
          "307",
          "308"
        ]
      },
      "behaviour": {
        "isOpeningNewTab": true,
        "externalUrl": "https://vault.bitwarden.com/#/login"
      },
      "area": {
        "type": "wrapper",
        "properties": {
          "id": "default"
        }
      },
      "shape": {
        "lg": {
          "location": {
            "x": 5,
            "y": 0
          },
          "size": {
            "width": 1,
            "height": 1
          }
        },
        "md": {
          "location": {
            "x": 4,
            "y": 3
          },
          "size": {
            "width": 1,
            "height": 1
          }
        }
      },
      "integration": {
        "type": null,
        "properties": []
      }
    },
    {
      "id": "266bb50c-7222-4b69-b3fa-9352f5f6018e",
      "name": "Outlook",
      "url": "https://outlook.live.com/mail/0/",
      "appearance": {
        "iconUrl": "https://cdn.jsdelivr.net/gh/PapirusDevelopmentTeam/papirus_icons/src/apps_microsoft_outlook.svg",
        "appNameStatus": "normal",
        "positionAppName": "column",
        "lineClampAppName": 1,
        "appNameFontSize": 16
      },
      "network": {
        "enabledStatusChecker": true,
        "statusCodes": [
          "200"
        ]
      },
      "behaviour": {
        "isOpeningNewTab": true,
        "externalUrl": "https://outlook.live.com/mail/0/"
      },
      "area": {
        "type": "wrapper",
        "properties": {
          "id": "default"
        }
      },
      "shape": {
        "lg": {
          "location": {
            "x": 10,
            "y": 2
          },
          "size": {
            "width": 1,
            "height": 1
          }
        },
        "md": {
          "location": {
            "x": 5,
            "y": 2
          },
          "size": {
            "width": 1,
            "height": 1
          }
        }
      },
      "integration": {
        "type": null,
        "properties": []
      }
    },
    {
      "id": "d6868f99-c99a-4cc1-a180-bb06c6c70484",
      "name": "Spotify",
      "url": "https://open.spotify.com/",
      "appearance": {
        "iconUrl": "https://cdn.jsdelivr.net/gh/walkxcode/dashboard-icons/png/spotify.png",
        "appNameStatus": "normal",
        "positionAppName": "column",
        "lineClampAppName": 1,
        "appNameFontSize": 16
      },
      "network": {
        "enabledStatusChecker": true,
        "statusCodes": [
          "200",
          "301",
          "302",
          "304",
          "307",
          "308"
        ]
      },
      "behaviour": {
        "isOpeningNewTab": true,
        "externalUrl": "https://open.spotify.com/"
      },
      "area": {
        "type": "wrapper",
        "properties": {
          "id": "default"
        }
      },
      "shape": {
        "lg": {
          "location": {
            "x": 9,
            "y": 2
          },
          "size": {
            "width": 1,
            "height": 1
          }
        },
        "md": {
          "location": {
            "x": 4,
            "y": 4
          },
          "size": {
            "width": 1,
            "height": 1
          }
        }
      },
      "integration": {
        "type": null,
        "properties": []
      }
    },
    {
      "id": "9594c743-4d33-4946-a7d2-87cfab739629",
      "name": "IT-Tool",
      "url": "https://it-tools.tech",
      "appearance": {
        "iconUrl": "https://cdn.jsdelivr.net/gh/walkxcode/dashboard-icons/svg/it-tools-light.svg",
        "appNameStatus": "normal",
        "positionAppName": "column",
        "lineClampAppName": 1,
        "appNameFontSize": 16
      },
      "network": {
        "enabledStatusChecker": true,
        "statusCodes": [
          "200",
          "301",
          "302",
          "304",
          "307",
          "308"
        ]
      },
      "behaviour": {
        "isOpeningNewTab": true,
        "externalUrl": "https://it-tools.tech/"
      },
      "area": {
        "type": "sidebar",
        "properties": {
          "location": "right"
        }
      },
      "shape": {
        "lg": {
          "location": {
            "x": 0,
            "y": 8
          },
          "size": {
            "width": 1,
            "height": 1
          }
        }
      },
      "integration": {
        "type": null,
        "properties": []
      }
    },
    {
      "id": "0d3b72ec-f925-4296-b966-1dc160694559",
      "name": "Qbit",
      "url": "https://qbit.virtual.lontiotlabs.au",
      "appearance": {
        "iconUrl": "https://cdn.jsdelivr.net/gh/walkxcode/dashboard-icons/png/qbittorrent.png",
        "appNameStatus": "normal",
        "positionAppName": "column",
        "lineClampAppName": 1,
        "appNameFontSize": 16
      },
      "network": {
        "enabledStatusChecker": true,
        "statusCodes": [
          "200"
        ]
      },
      "behaviour": {
        "isOpeningNewTab": true,
        "externalUrl": "https://qbit.virtual.lontiotlabs.au"
      },
      "area": {
        "type": "wrapper",
        "properties": {
          "id": "default"
        }
      },
      "shape": {
        "lg": {
          "location": {
            "x": 9,
            "y": 0
          },
          "size": {
            "width": 1,
            "height": 1
          }
        },
        "md": {
          "location": {
            "x": 5,
            "y": 4
          },
          "size": {
            "width": 1,
            "height": 1
          }
        }
      },
      "integration": {
        "type": "qBittorrent",
        "properties": [
          {
            "field": "username",
            "type": "public",
            "value": "admin"
          },
          {
            "field": "password",
            "type": "private",
            "value": "adminadmin"
          }
        ]
      }
    },
    {
      "id": "d2bd9f19-3a6f-414f-adba-61d7fdf510fd",
      "name": "Photos",
      "url": "https://photos.google.com/",
      "appearance": {
        "iconUrl": "https://cdn.jsdelivr.net/gh/walkxcode/dashboard-icons/png/google-photos.png",
        "appNameStatus": "normal",
        "positionAppName": "column",
        "lineClampAppName": 1,
        "appNameFontSize": 16
      },
      "network": {
        "enabledStatusChecker": true,
        "statusCodes": [
          "200",
          "301",
          "302",
          "304",
          "307",
          "308"
        ]
      },
      "behaviour": {
        "isOpeningNewTab": true,
        "externalUrl": "https://photos.google.com/"
      },
      "area": {
        "type": "wrapper",
        "properties": {
          "id": "default"
        }
      },
      "shape": {
        "lg": {
          "location": {
            "x": 11,
            "y": 2
          },
          "size": {
            "width": 1,
            "height": 1
          }
        },
        "md": {
          "location": {
            "x": 3,
            "y": 3
          },
          "size": {
            "width": 1,
            "height": 1
          }
        }
      },
      "integration": {
        "type": null,
        "properties": []
      }
    },
    {
      "id": "4ef5286a-a4eb-4f61-a7e6-c2860fd6d7c4",
      "name": "AGL",
      "url": "https://myaccount.agl.com.au/",
      "appearance": {
        "iconUrl": "https://www.channelnews.com.au/wp-content/uploads/2021/02/1200px-AGL_Energy_logo-400x300.png",
        "appNameStatus": "normal",
        "positionAppName": "column",
        "lineClampAppName": 1,
        "appNameFontSize": 16
      },
      "network": {
        "enabledStatusChecker": true,
        "statusCodes": [
          "200",
          "301",
          "302",
          "304",
          "307",
          "308"
        ]
      },
      "behaviour": {
        "isOpeningNewTab": true,
        "externalUrl": "https://myaccount.agl.com.au/"
      },
      "area": {
        "type": "wrapper",
        "properties": {
          "id": "default"
        }
      },
      "shape": {
        "lg": {
          "location": {
            "x": 9,
            "y": 6
          },
          "size": {
            "width": 1,
            "height": 1
          }
        },
        "md": {
          "location": {
            "x": 0,
            "y": 1
          },
          "size": {
            "width": 1,
            "height": 1
          }
        }
      },
      "integration": {
        "type": null,
        "properties": []
      }
    },
    {
      "id": "39445721-7f7b-46a3-9b91-866e52e91b23",
      "name": "Core",
      "url": "https://core-electronics.com.au/",
      "appearance": {
        "iconUrl": "https://core-electronics.com.au/media/wysiwyg/resources/core-electronics-logo-social3.png",
        "appNameStatus": "normal",
        "positionAppName": "column",
        "lineClampAppName": 1,
        "appNameFontSize": 16
      },
      "network": {
        "enabledStatusChecker": true,
        "statusCodes": [
          "200"
        ]
      },
      "behaviour": {
        "isOpeningNewTab": true,
        "externalUrl": "https://core-electronics.com.au/"
      },
      "area": {
        "type": "wrapper",
        "properties": {
          "id": "default"
        }
      },
      "shape": {
        "lg": {
          "location": {
            "x": 5,
            "y": 7
          },
          "size": {
            "width": 1,
            "height": 1
          }
        },
        "md": {
          "location": {
            "x": 5,
            "y": 3
          },
          "size": {
            "width": 1,
            "height": 1
          }
        }
      },
      "integration": {
        "type": null,
        "properties": []
      }
    },
    {
      "id": "dc4c8397-4845-47c0-8ff0-7891dc74ef14",
      "name": "Bunnings",
      "url": "https://www.bunnings.com.au/",
      "appearance": {
        "iconUrl": "https://play-lh.googleusercontent.com/MWhqOFIdHluMh6YL4O-3UTGwhT9q8D8K5X7WnAzN3AbcNAzRRcYUPLuXLQWbHAhNKg",
        "appNameStatus": "normal",
        "positionAppName": "column",
        "lineClampAppName": 1,
        "appNameFontSize": 16
      },
      "network": {
        "enabledStatusChecker": true,
        "statusCodes": [
          "200",
          "301",
          "302",
          "304",
          "307",
          "308"
        ]
      },
      "behaviour": {
        "isOpeningNewTab": true,
        "externalUrl": "https://www.bunnings.com.au/"
      },
      "area": {
        "type": "wrapper",
        "properties": {
          "id": "default"
        }
      },
      "shape": {
        "lg": {
          "location": {
            "x": 6,
            "y": 7
          },
          "size": {
            "width": 1,
            "height": 1
          }
        },
        "md": {
          "location": {
            "x": 2,
            "y": 0
          },
          "size": {
            "width": 1,
            "height": 1
          }
        }
      },
      "integration": {
        "type": null,
        "properties": []
      }
    },
    {
      "id": "2f93d783-704c-47df-81e7-bdea6e641286",
      "name": "Timbercon",
      "url": "https://www.timbecon.com.au",
      "appearance": {
        "iconUrl": "https://encrypted-tbn0.gstatic.com/images?q=tbn:ANd9GcTh7br_Ut6MHq0e6pX0CuAQ9tygFDRRuh0xCA&s",
        "appNameStatus": "normal",
        "positionAppName": "column",
        "lineClampAppName": 1,
        "appNameFontSize": 16
      },
      "network": {
        "enabledStatusChecker": true,
        "statusCodes": [
          "200",
          "301",
          "302",
          "304",
          "307",
          "308"
        ]
      },
      "behaviour": {
        "isOpeningNewTab": true,
        "externalUrl": "https://www.timbecon.com.au/"
      },
      "area": {
        "type": "wrapper",
        "properties": {
          "id": "default"
        }
      },
      "shape": {
        "lg": {
          "location": {
            "x": 7,
            "y": 7
          },
          "size": {
            "width": 1,
            "height": 1
          }
        }
      },
      "integration": {
        "type": null,
        "properties": []
      }
    },
    {
      "id": "7f7acdea-2f8e-48cb-914d-8ed948c5c85d",
      "name": "More",
      "url": "https://myaccount.more.com.au/",
      "appearance": {
        "iconUrl": "https://static.thenounproject.com/png/1947307-200.png",
        "appNameStatus": "normal",
        "positionAppName": "column",
        "lineClampAppName": 1,
        "appNameFontSize": 16
      },
      "network": {
        "enabledStatusChecker": true,
        "statusCodes": [
          "200",
          "301",
          "302",
          "304",
          "307",
          "308"
        ]
      },
      "behaviour": {
        "isOpeningNewTab": true,
        "externalUrl": "https://myaccount.more.com.au/"
      },
      "area": {
        "type": "wrapper",
        "properties": {
          "id": "default"
        }
      },
      "shape": {
        "lg": {
          "location": {
            "x": 9,
            "y": 7
          },
          "size": {
            "width": 1,
            "height": 1
          }
        },
        "md": {
          "location": {
            "x": 3,
            "y": 6
          },
          "size": {
            "width": 1,
            "height": 1
          }
        }
      },
      "integration": {
        "type": null,
        "properties": []
      }
    },
    {
      "id": "984415fb-d804-4f7b-89be-9c17d3f2f59d",
      "name": "Tdarr",
      "url": "https://tdarr.virtual.lontiotlabs.au",
      "appearance": {
        "iconUrl": "https://cdn.jsdelivr.net/gh/walkxcode/dashboard-icons/png/tdarr.png",
        "appNameStatus": "normal",
        "positionAppName": "column",
        "lineClampAppName": 1,
        "appNameFontSize": 16
      },
      "network": {
        "enabledStatusChecker": true,
        "statusCodes": [
          "200"
        ]
      },
      "behaviour": {
        "isOpeningNewTab": true,
        "externalUrl": "https://tdarr.virtual.lontiotlabs.au"
      },
      "area": {
        "type": "wrapper",
        "properties": {
          "id": "default"
        }
      },
      "shape": {
        "lg": {
          "location": {
            "x": 11,
            "y": 1
          },
          "size": {
            "width": 1,
            "height": 1
          }
        },
        "md": {
          "location": {
            "x": 0,
            "y": 5
          },
          "size": {
            "width": 1,
            "height": 1
          }
        }
      },
      "integration": {
        "type": null,
        "properties": []
      }
    },
    {
      "id": "11e9024f-d91b-4fbb-8473-525ea7c0dabc",
      "name": "Budget",
      "url": "https://budget.virtual.lontiotlabs.au",
      "appearance": {
        "iconUrl": "https://www.dumbware.io/software/DumbBudget/dumbbudget.svg",
        "appNameStatus": "normal",
        "positionAppName": "column",
        "lineClampAppName": 1,
        "appNameFontSize": 16
      },
      "network": {
        "enabledStatusChecker": true,
        "statusCodes": [
          "200",
          "301",
          "302",
          "304",
          "307",
          "308"
        ]
      },
      "behaviour": {
        "isOpeningNewTab": true,
        "externalUrl": "https://budget.virtual.lontiotlabs.au"
      },
      "area": {
        "type": "sidebar",
        "properties": {
          "location": "right"
        }
      },
      "shape": {
        "lg": {
          "location": {
            "x": 1,
            "y": 7
          },
          "size": {
            "width": 1,
            "height": 1
          }
        }
      },
      "integration": {
        "type": null,
        "properties": []
      }
    },
    {
      "id": "89b9f82c-bffb-46e2-81fe-1659669800b7",
      "name": "PiHole",
      "url": "https://pihole.lontiotlabs.au/admin",
      "appearance": {
        "iconUrl": "https://upload.wikimedia.org/wikipedia/commons/0/00/Pi-hole_Logo.png",
        "appNameStatus": "normal",
        "positionAppName": "column",
        "lineClampAppName": 1,
        "appNameFontSize": 16
      },
      "network": {
        "enabledStatusChecker": true,
        "statusCodes": [
          "200"
        ]
      },
      "behaviour": {
        "isOpeningNewTab": true,
        "externalUrl": "https://pihole.lontiotlabs.au/admin"
      },
      "area": {
        "type": "wrapper",
        "properties": {
          "id": "default"
        }
      },
      "shape": {
        "lg": {
          "location": {
            "x": 8,
            "y": 1
          },
          "size": {
            "width": 1,
            "height": 1
          }
        },
        "md": {
          "location": {
            "x": 1,
            "y": 5
          },
          "size": {
            "width": 1,
            "height": 1
          }
        }
      },
      "integration": {
        "type": null,
        "properties": []
      }
    },
    {
      "id": "f3684dce-0285-4bf3-8b8f-418500baad11",
      "name": "Proxmox",
      "url": "https://proxmox.virtual.lontiotlabs.au",
      "appearance": {
        "iconUrl": "https://cdn.jsdelivr.net/gh/walkxcode/dashboard-icons/png/proxmox.png",
        "appNameStatus": "normal",
        "positionAppName": "column",
        "lineClampAppName": 1,
        "appNameFontSize": 16
      },
      "network": {
        "enabledStatusChecker": true,
        "statusCodes": [
          "200"
        ]
      },
      "behaviour": {
        "isOpeningNewTab": true,
        "externalUrl": "https://proxmox.virtual.lontiotlabs.au"
      },
      "area": {
        "type": "sidebar",
        "properties": {
          "location": "right"
        }
      },
      "shape": {
        "lg": {
          "location": {
            "x": 1,
            "y": 1
          },
          "size": {
            "width": 1,
            "height": 1
          }
        },
        "md": {
          "location": {
            "x": 0,
            "y": 1
          },
          "size": {
            "width": 1,
            "height": 1
          }
        }
      },
      "integration": {
        "type": null,
        "properties": []
      }
    },
    {
      "id": "8e108e17-635f-44c8-b395-a4dd389751a3",
      "name": "PiHole-Backup",
      "url": "https://pihole-backup.lontiotlabs.au/admin",
      "appearance": {
        "iconUrl": "https://upload.wikimedia.org/wikipedia/commons/0/00/Pi-hole_Logo.png",
        "appNameStatus": "normal",
        "positionAppName": "column",
        "lineClampAppName": 1,
        "appNameFontSize": 16
      },
      "network": {
        "enabledStatusChecker": true,
        "statusCodes": [
          "200"
        ]
      },
      "behaviour": {
        "isOpeningNewTab": true,
        "externalUrl": "https://pihole-backup.lontiotlabs.au/admin"
      },
      "area": {
        "type": "wrapper",
        "properties": {
          "id": "default"
        }
      },
      "shape": {
        "lg": {
          "location": {
            "x": 9,
            "y": 1
          },
          "size": {
            "width": 1,
            "height": 1
          }
        },
        "md": {
          "location": {
            "x": 2,
            "y": 5
          },
          "size": {
            "width": 1,
            "height": 1
          }
        }
      },
      "integration": {
        "type": null,
        "properties": []
      }
    },
    {
      "id": "dbd7fea6-0b79-4e40-b406-ce05126744a3",
      "name": "Pad",
      "url": "https://pad.virtual.lontiotlabs.au",
      "appearance": {
        "iconUrl": "https://cdn.jsdelivr.net/gh/walkxcode/dashboard-icons/svg/dumbpad.svg",
        "appNameStatus": "normal",
        "positionAppName": "column",
        "lineClampAppName": 1,
        "appNameFontSize": 16
      },
      "network": {
        "enabledStatusChecker": true,
        "statusCodes": [
          "200",
          "301",
          "302",
          "304",
          "307",
          "308"
        ]
      },
      "behaviour": {
        "isOpeningNewTab": true,
        "externalUrl": "https://pad.virtual.lontiotlabs.au"
      },
      "area": {
        "type": "sidebar",
        "properties": {
          "location": "right"
        }
      },
      "shape": {
        "lg": {
          "location": {
            "x": 1,
            "y": 6
          },
          "size": {
            "width": 1,
            "height": 1
          }
        }
      },
      "integration": {
        "type": null,
        "properties": []
      }
    },
    {
      "id": "f54c1972-ec9d-4cbc-9609-9b64b00579a7",
      "name": "nextcloud",
      "url": "https://nextcloud.lontiotlabs.au",
      "appearance": {
        "iconUrl": "https://cdn.jsdelivr.net/gh/walkxcode/dashboard-icons/svg/nextcloud-blue.svg",
        "appNameStatus": "normal",
        "positionAppName": "column",
        "lineClampAppName": 1,
        "appNameFontSize": 16
      },
      "network": {
        "enabledStatusChecker": true,
        "statusCodes": [
          "200",
          "301",
          "302",
          "304",
          "307",
          "308"
        ]
      },
      "behaviour": {
        "isOpeningNewTab": true,
        "externalUrl": "https://nextcloud.lontiotlabs.au"
      },
      "area": {
        "type": "sidebar",
        "properties": {
          "location": "right"
        }
      },
      "shape": {
        "lg": {
          "location": {
            "x": 0,
            "y": 2
          },
          "size": {
            "width": 1,
            "height": 1
          }
        },
        "md": {
          "location": {
            "x": 0,
            "y": 5
          },
          "size": {
            "width": 1,
            "height": 1
          }
        }
      },
      "integration": {
        "type": null,
        "properties": []
      }
    },
    {
      "id": "9416a608-8e42-46fb-a8e8-8249fac457b6",
      "name": "Reolink",
      "url": "https://nvr.iot.lontiotlabs.au",
      "appearance": {
        "iconUrl": "https://play-lh.googleusercontent.com/Tw6F1NidIp4yqzM8J2Eul923mrK0l5qxkqbnGybtOxU6torgHZo5VQ4bwICr0RAgF7Y",
        "appNameStatus": "normal",
        "positionAppName": "column",
        "lineClampAppName": 1,
        "appNameFontSize": 16
      },
      "network": {
        "enabledStatusChecker": true,
        "statusCodes": [
          "200",
          "301",
          "302",
          "304",
          "307",
          "308"
        ]
      },
      "behaviour": {
        "isOpeningNewTab": true,
        "externalUrl": "https://nvr.iot.lontiotlabs.au"
      },
      "area": {
        "type": "sidebar",
        "properties": {
          "location": "right"
        }
      },
      "shape": {
        "lg": {
          "location": {
            "x": 1,
            "y": 8
          },
          "size": {
            "width": 1,
            "height": 1
          }
        },
        "md": {
          "location": {
            "x": 1,
            "y": 2
          },
          "size": {
            "width": 1,
            "height": 1
          }
        }
      },
      "integration": {
        "type": null,
        "properties": []
      }
    },
    {
      "id": "1e7f4756-052c-4449-a80c-b10b1523aece",
      "name": "Gotify",
      "url": "https://gotify.lontiotlabs.au",
      "appearance": {
        "iconUrl": "https://cdn.jsdelivr.net/gh/walkxcode/dashboard-icons/svg/gotify.svg",
        "appNameStatus": "normal",
        "positionAppName": "column",
        "lineClampAppName": 1,
        "appNameFontSize": 16
      },
      "network": {
        "enabledStatusChecker": true,
        "statusCodes": [
          "200",
          "301",
          "302",
          "304",
          "307",
          "308"
        ]
      },
      "behaviour": {
        "isOpeningNewTab": true,
        "externalUrl": "https://gotify.lontiotlabs.au"
      },
      "area": {
        "type": "sidebar",
        "properties": {
          "location": "right"
        }
      },
      "shape": {
        "lg": {
          "location": {
            "x": 0,
            "y": 3
          },
          "size": {
            "width": 1,
            "height": 1
          }
        }
      },
      "integration": {
        "type": null,
        "properties": []
      }
    },
    {
      "id": "1740f7a7-a04c-41d5-a381-1e7892128e6b",
      "name": "Jackett",
      "url": "https://jackett.virtual.lontiotlabs.au",
      "appearance": {
        "iconUrl": "https://cdn.jsdelivr.net/gh/walkxcode/dashboard-icons/png/jackett.png",
        "appNameStatus": "normal",
        "positionAppName": "column",
        "lineClampAppName": 1,
        "appNameFontSize": 16
      },
      "network": {
        "enabledStatusChecker": true,
        "statusCodes": [
          "200"
        ]
      },
      "behaviour": {
        "isOpeningNewTab": true,
        "externalUrl": "https://jackett.virtual.lontiotlabs.au"
      },
      "area": {
        "type": "wrapper",
        "properties": {
          "id": "default"
        }
      },
      "shape": {
        "lg": {
          "location": {
            "x": 10,
            "y": 0
          },
          "size": {
            "width": 1,
            "height": 1
          }
        },
        "md": {
          "location": {
            "x": 3,
            "y": 0
          },
          "size": {
            "width": 1,
            "height": 1
          }
        }
      },
      "integration": {
        "type": null,
        "properties": []
      }
    },
    {
      "id": "23163220-bc19-45fc-bbf6-6cb8d0d2506e",
      "name": "Commbank",
      "url": "https://www.commbank.com.au/retail/netbank/home/",
      "appearance": {
        "iconUrl": "https://upload.wikimedia.org/wikipedia/en/thumb/9/9c/Commonwealth_Bank_logo_2020.svg/1200px-Commonwealth_Bank_logo_2020.svg.png",
        "appNameStatus": "normal",
        "positionAppName": "column",
        "lineClampAppName": 1,
        "appNameFontSize": 16
      },
      "network": {
        "enabledStatusChecker": true,
        "statusCodes": [
          "200"
        ]
      },
      "behaviour": {
        "isOpeningNewTab": true,
        "externalUrl": "https://www.commbank.com.au/retail/netbank/home/"
      },
      "area": {
        "type": "sidebar",
        "properties": {
          "location": "right"
        }
      },
      "shape": {
        "lg": {
          "location": {
            "x": 1,
            "y": 2
          },
          "size": {
            "width": 1,
            "height": 1
          }
        },
        "md": {
          "location": {
            "x": 0,
            "y": 2
          },
          "size": {
            "width": 1,
            "height": 1
          }
        }
      },
      "integration": {
        "type": null,
        "properties": []
      }
    },
    {
      "id": "7bf8a7b1-282d-4976-982c-38079007af38",
      "name": "Bazarr",
      "url": "https://bazarr.virtual.lontiotlabs.au",
      "appearance": {
        "iconUrl": "https://cdn.jsdelivr.net/gh/walkxcode/dashboard-icons/png/bazarr.png",
        "appNameStatus": "normal",
        "positionAppName": "column",
        "lineClampAppName": 1,
        "appNameFontSize": 16
      },
      "network": {
        "enabledStatusChecker": true,
        "statusCodes": [
          "200"
        ]
      },
      "behaviour": {
        "isOpeningNewTab": true,
        "externalUrl": "https://bazarr.virtual.lontiotlabs.au"
      },
      "area": {
        "type": "wrapper",
        "properties": {
          "id": "default"
        }
      },
      "shape": {
        "lg": {
          "location": {
            "x": 11,
            "y": 0
          },
          "size": {
            "width": 1,
            "height": 1
          }
        },
        "md": {
          "location": {
            "x": 4,
            "y": 0
          },
          "size": {
            "width": 1,
            "height": 1
          }
        }
      },
      "integration": {
        "type": null,
        "properties": []
      }
    },
    {
      "id": "c9954075-e3f7-4f77-b842-7289f6c26c6c",
      "name": "Asset",
      "url": "https://assets.virtual.lontiotlabs.au",
      "appearance": {
        "iconUrl": "https://cdn.jsdelivr.net/gh/walkxcode/dashboard-icons/svg/dumbassets.svg",
        "appNameStatus": "normal",
        "positionAppName": "column",
        "lineClampAppName": 1,
        "appNameFontSize": 16
      },
      "network": {
        "enabledStatusChecker": true,
        "statusCodes": [
          "200",
          "301",
          "302",
          "304",
          "307",
          "308"
        ]
      },
      "behaviour": {
        "isOpeningNewTab": true,
        "externalUrl": "https://assets.virtual.lontiotlabs.au"
      },
      "area": {
        "type": "sidebar",
        "properties": {
          "location": "right"
        }
      },
      "shape": {
        "lg": {
          "location": {
            "x": 0,
            "y": 5
          },
          "size": {
            "width": 1,
            "height": 1
          }
        }
      },
      "integration": {
        "type": null,
        "properties": []
      }
    },
    {
      "id": "c3d1720d-a868-46a9-91d3-d81de0289a5b",
      "name": "Amazon",
      "url": "https://www.amazon.com.au/",
      "appearance": {
        "iconUrl": "https://cdn.jsdelivr.net/gh/walkxcode/dashboard-icons/png/amazon.png",
        "appNameStatus": "normal",
        "positionAppName": "column",
        "lineClampAppName": 1,
        "appNameFontSize": 16
      },
      "network": {
        "enabledStatusChecker": true,
        "statusCodes": [
          "200"
        ]
      },
      "behaviour": {
        "isOpeningNewTab": true,
        "externalUrl": "https://www.amazon.com.au/"
      },
      "area": {
        "type": "wrapper",
        "properties": {
          "id": "default"
        }
      },
      "shape": {
        "lg": {
          "location": {
            "x": 4,
            "y": 7
          },
          "size": {
            "width": 1,
            "height": 1
          }
        },
        "md": {
          "location": {
            "x": 1,
            "y": 1
          },
          "size": {
            "width": 1,
            "height": 1
          }
        }
      },
      "integration": {
        "type": null,
        "properties": []
      }
    },
    {
      "id": "7d49c090-8c6c-4399-b0d5-409eeff50225",
      "name": "ntfy",
      "url": "https://notify.lontiotlabs.au",
      "appearance": {
        "iconUrl": "https://cdn.jsdelivr.net/gh/walkxcode/dashboard-icons/svg/ntfy.svg",
        "appNameStatus": "normal",
        "positionAppName": "column",
        "lineClampAppName": 1,
        "appNameFontSize": 16
      },
      "network": {
        "enabledStatusChecker": true,
        "statusCodes": [
          "200",
          "301",
          "302",
          "304",
          "307",
          "308"
        ]
      },
      "behaviour": {
        "isOpeningNewTab": true,
        "externalUrl": "https://notify.lontiotlabs.au/"
      },
      "area": {
        "type": "sidebar",
        "properties": {
          "location": "right"
        }
      },
      "shape": {
        "lg": {
          "location": {
            "x": 0,
            "y": 4
          },
          "size": {
            "width": 1,
            "height": 1
          }
        },
        "md": {
          "location": {
            "x": 1,
            "y": 4
          },
          "size": {
            "width": 1,
            "height": 1
          }
        }
      },
      "integration": {
        "type": null,
        "properties": []
      }
    },
    {
      "id": "0f66e55f-be55-4ff6-bfe6-417c4c93c242",
      "name": "Home Assistant",
      "url": "https://homeassistant.lontiotlabs.au",
      "appearance": {
        "iconUrl": "https://cdn.jsdelivr.net/gh/walkxcode/dashboard-icons/svg/home-assistant.svg",
        "appNameStatus": "normal",
        "positionAppName": "column",
        "lineClampAppName": 1,
        "appNameFontSize": 16
      },
      "network": {
        "enabledStatusChecker": true,
        "statusCodes": [
          "200"
        ]
      },
      "behaviour": {
        "isOpeningNewTab": true,
        "externalUrl": "https://homeassistant.lontiotlabs.au"
      },
      "area": {
        "type": "sidebar",
        "properties": {
          "location": "right"
        }
      },
      "shape": {
        "lg": {
          "location": {
            "x": 0,
            "y": 0
          },
          "size": {
            "width": 1,
            "height": 1
          }
        },
        "md": {
          "location": {
            "x": 0,
            "y": 0
          },
          "size": {
            "width": 1,
            "height": 1
          }
        }
      },
      "integration": {
        "type": null,
        "properties": []
      }
    },
    {
      "id": "403c3c34-13ad-40f5-ad72-31d45c7b5491",
      "name": "Lidarr",
      "url": "https://lidarr.virtual.lontiotlabs.au",
      "appearance": {
        "iconUrl": "https://cdn.jsdelivr.net/gh/walkxcode/dashboard-icons/svg/lidarr.svg",
        "appNameStatus": "normal",
        "positionAppName": "column",
        "lineClampAppName": 1,
        "appNameFontSize": 16
      },
      "network": {
        "enabledStatusChecker": true,
        "statusCodes": [
          "200",
          "301",
          "302",
          "304",
          "307",
          "308"
        ]
      },
      "behaviour": {
        "isOpeningNewTab": true,
        "externalUrl": "https://lidarr.virtual.lontiotlabs.au"
      },
      "area": {
        "type": "wrapper",
        "properties": {
          "id": "default"
        }
      },
      "shape": {
        "lg": {
          "location": {
            "x": 6,
            "y": 0
          },
          "size": {
            "width": 1,
            "height": 1
          }
        }
      },
      "integration": {
        "type": null,
        "properties": []
      }
    },
    {
      "id": "afa4fbe5-6a5f-486f-96c9-2a6ddc357b5a",
      "name": "Drop",
      "url": "https://drop.lontiotlabs.au",
      "appearance": {
        "iconUrl": "https://www.dumbware.io/software/DumbDrop/dumbdrop.svg",
        "appNameStatus": "normal",
        "positionAppName": "column",
        "lineClampAppName": 1,
        "appNameFontSize": 16
      },
      "network": {
        "enabledStatusChecker": true,
        "statusCodes": [
          "200",
          "301",
          "302",
          "304",
          "307",
          "308"
        ]
      },
      "behaviour": {
        "isOpeningNewTab": true,
        "externalUrl": "https://drop.lontiotlabs.au"
      },
      "area": {
        "type": "sidebar",
        "properties": {
          "location": "right"
        }
      },
      "shape": {
        "lg": {
          "location": {
            "x": 1,
            "y": 5
          },
          "size": {
            "width": 1,
            "height": 1
          }
        }
      },
      "integration": {
        "type": null,
        "properties": []
      }
    },
    {
      "id": "42f5588f-1bf6-4606-9f5c-dbf450e008c3",
      "name": "Sonarr",
      "url": "https://sonarr.virtual.lontiotlabs.au",
      "appearance": {
        "iconUrl": "https://cdn.jsdelivr.net/gh/walkxcode/dashboard-icons/png/sonarr.png",
        "appNameStatus": "normal",
        "positionAppName": "column",
        "lineClampAppName": 1,
        "appNameFontSize": 16
      },
      "network": {
        "enabledStatusChecker": true,
        "statusCodes": [
          "200"
        ]
      },
      "behaviour": {
        "isOpeningNewTab": true,
        "externalUrl": "https://sonarr.virtual.lontiotlabs.au"
      },
      "area": {
        "type": "wrapper",
        "properties": {
          "id": "default"
        }
      },
      "shape": {
        "lg": {
          "location": {
            "x": 7,
            "y": 0
          },
          "size": {
            "width": 1,
            "height": 1
          }
        },
        "md": {
          "location": {
            "x": 2,
            "y": 2
          },
          "size": {
            "width": 1,
            "height": 1
          }
        }
      },
      "integration": {
        "type": "sonarr",
        "properties": [
          {
            "field": "apiKey",
            "type": "private",
            "value": "57d1fd6c61894aa2b4e5a6b65b7b4104"
          }
        ]
      }
    },
    {
      "id": "c8c16f53-2ef8-4782-9ba9-f7cf377e925f",
      "name": "Todo",
      "url": "https://todo.virtual.lontiotlabs.au",
      "appearance": {
        "iconUrl": "https://www.dumbware.io/software/DumbDo/dumbdo.svg",
        "appNameStatus": "normal",
        "positionAppName": "column",
        "lineClampAppName": 1,
        "appNameFontSize": 16
      },
      "network": {
        "enabledStatusChecker": true,
        "statusCodes": [
          "200",
          "301",
          "302",
          "304",
          "307",
          "308"
        ]
      },
      "behaviour": {
        "isOpeningNewTab": true,
        "externalUrl": "https://todo.virtual.lontiotlabs.au"
      },
      "area": {
        "type": "sidebar",
        "properties": {
          "location": "right"
        }
      },
      "shape": {
        "lg": {
          "location": {
            "x": 1,
            "y": 4
          },
          "size": {
            "width": 1,
            "height": 1
          }
        }
      },
      "integration": {
        "type": null,
        "properties": []
      }
    },
    {
      "id": "0f573e8d-f3c8-4ecd-baf5-550befaaba9a",
      "name": "Youtube",
      "url": "https://www.youtube.com/",
      "appearance": {
        "iconUrl": "https://cdn.jsdelivr.net/gh/walkxcode/dashboard-icons/png/youtube.png",
        "appNameStatus": "normal",
        "positionAppName": "column",
        "lineClampAppName": 1,
        "appNameFontSize": 16
      },
      "network": {
        "enabledStatusChecker": true,
        "statusCodes": [
          "200"
        ]
      },
      "behaviour": {
        "isOpeningNewTab": true,
        "externalUrl": "https://www.youtube.com/"
      },
      "area": {
        "type": "wrapper",
        "properties": {
          "id": "default"
        }
      },
      "shape": {
        "lg": {
          "location": {
            "x": 8,
            "y": 2
          },
          "size": {
            "width": 1,
            "height": 1
          }
        },
        "md": {
          "location": {
            "x": 3,
            "y": 2
          },
          "size": {
            "width": 1,
            "height": 1
          }
        }
      },
      "integration": {
        "type": null,
        "properties": []
      }
    },
    {
      "id": "4ba2194c-7028-4cb7-bee0-fdb55901c3c5",
      "name": "Semaphore",
      "url": "https://ansible.virtual.lontiotlabs.au",
      "appearance": {
        "iconUrl": "https://avatars.githubusercontent.com/u/98574287?v=4",
        "appNameStatus": "normal",
        "positionAppName": "column",
        "lineClampAppName": 1,
        "appNameFontSize": 16
      },
      "network": {
        "enabledStatusChecker": true,
        "statusCodes": [
          "200",
          "301",
          "302",
          "304",
          "307",
          "308"
        ]
      },
      "behaviour": {
        "isOpeningNewTab": true,
        "externalUrl": "https://ansible.virtual.lontiotlabs.au/"
      },
      "area": {
        "type": "sidebar",
        "properties": {
          "location": "right"
        }
      },
      "shape": {
        "lg": {
          "location": {
            "x": 0,
            "y": 6
          },
          "size": {
            "width": 1,
            "height": 1
          }
        }
      },
      "integration": {
        "type": null,
        "properties": []
      }
    },
    {
      "id": "2b2f89b7-c9f1-47e6-aaa9-a17b6556152a",
      "name": "Omada",
      "url": "https://omada.lontiotlabs.au",
      "appearance": {
        "iconUrl": "https://cdn.jsdelivr.net/gh/walkxcode/dashboard-icons/png/omada.png",
        "appNameStatus": "normal",
        "positionAppName": "column",
        "lineClampAppName": 1,
        "appNameFontSize": 16
      },
      "network": {
        "enabledStatusChecker": true,
        "statusCodes": [
          "200"
        ]
      },
      "behaviour": {
        "isOpeningNewTab": true,
        "externalUrl": "https://omada.lontiotlabs.au"
      },
      "area": {
        "type": "sidebar",
        "properties": {
          "location": "right"
        }
      },
      "shape": {
        "lg": {
          "location": {
            "x": 1,
            "y": 0
          },
          "size": {
            "width": 1,
            "height": 1
          }
        },
        "md": {
          "location": {
            "x": 1,
            "y": 1
          },
          "size": {
            "width": 1,
            "height": 1
          }
        }
      },
      "integration": {
        "type": null,
        "properties": []
      }
    },
    {
      "id": "d021f2af-5d2f-49e4-aa13-6566c5e5a1ee",
      "name": "Organizr",
      "url": "https://organiser.virtual.lontiotlabs.au",
      "appearance": {
        "iconUrl": "https://cdn.jsdelivr.net/gh/walkxcode/dashboard-icons/png/organizr.png",
        "appNameStatus": "normal",
        "positionAppName": "column",
        "lineClampAppName": 1,
        "appNameFontSize": 16
      },
      "network": {
        "enabledStatusChecker": true,
        "statusCodes": [
          "200"
        ]
      },
      "behaviour": {
        "isOpeningNewTab": true,
        "externalUrl": "https://organiser.virtual.lontiotlabs.au"
      },
      "area": {
        "type": "wrapper",
        "properties": {
          "id": "default"
        }
      },
      "shape": {
        "lg": {
          "location": {
            "x": 7,
            "y": 1
          },
          "size": {
            "width": 1,
            "height": 1
          }
        },
        "md": {
          "location": {
            "x": 4,
            "y": 2
          },
          "size": {
            "width": 1,
            "height": 1
          }
        }
      },
      "integration": {
        "type": null,
        "properties": []
      }
    },
    {
      "id": "148c442b-e026-4842-8f16-ad0614bf769a",
      "name": "Truenas",
      "url": "https://truenas.lontiotlabs.au",
      "appearance": {
        "iconUrl": "https://cdn.jsdelivr.net/gh/walkxcode/dashboard-icons/png/truenas.png",
        "appNameStatus": "normal",
        "positionAppName": "column",
        "lineClampAppName": 1,
        "appNameFontSize": 16
      },
      "network": {
        "enabledStatusChecker": true,
        "statusCodes": [
          "200"
        ]
      },
      "behaviour": {
        "isOpeningNewTab": true,
        "externalUrl": "https://truenas.lontiotlabs.au/"
      },
      "area": {
        "type": "sidebar",
        "properties": {
          "location": "right"
        }
      },
      "shape": {
        "lg": {
          "location": {
            "x": 0,
            "y": 1
          },
          "size": {
            "width": 1,
            "height": 1
          }
        },
        "md": {
          "location": {
            "x": 1,
            "y": 0
          },
          "size": {
            "width": 1,
            "height": 1
          }
        }
      },
      "integration": {
        "type": null,
        "properties": []
      }
    },
    {
      "id": "c2045fb7-80f3-4262-8ab2-17d6fa945cc7",
      "name": "Netalertx",
      "url": "https://alerts.lontiotlabs.au",
      "appearance": {
        "iconUrl": "https://cdn.jsdelivr.net/gh/walkxcode/dashboard-icons/svg/netalertx-light.svg",
        "appNameStatus": "normal",
        "positionAppName": "column",
        "lineClampAppName": 1,
        "appNameFontSize": 16
      },
      "network": {
        "enabledStatusChecker": true,
        "statusCodes": [
          "200",
          "301",
          "302",
          "304",
          "307",
          "308"
        ]
      },
      "behaviour": {
        "isOpeningNewTab": true,
        "externalUrl": "https://alerts.lontiotlabs.au"
      },
      "area": {
        "type": "sidebar",
        "properties": {
          "location": "right"
        }
      },
      "shape": {
        "lg": {
          "location": {
            "x": 1,
            "y": 3
          },
          "size": {
            "width": 1,
            "height": 1
          }
        }
      },
      "integration": {
        "type": null,
        "properties": []
      }
    },
    {
      "id": "888454cf-4463-468f-96d2-7c63c778c360",
      "name": "Radarr",
      "url": "https://radarr.virtual.lontiotlabs.au",
      "appearance": {
        "iconUrl": "https://cdn.jsdelivr.net/gh/walkxcode/dashboard-icons/png/radarr.png",
        "appNameStatus": "normal",
        "positionAppName": "column",
        "lineClampAppName": 1,
        "appNameFontSize": 16
      },
      "network": {
        "enabledStatusChecker": true,
        "statusCodes": [
          "200"
        ]
      },
      "behaviour": {
        "isOpeningNewTab": true,
        "externalUrl": "https://radarr.virtual.lontiotlabs.au"
      },
      "area": {
        "type": "wrapper",
        "properties": {
          "id": "default"
        }
      },
      "shape": {
        "lg": {
          "location": {
            "x": 8,
            "y": 0
          },
          "size": {
            "width": 1,
            "height": 1
          }
        },
        "md": {
          "location": {
            "x": 0,
            "y": 3
          },
          "size": {
            "width": 1,
            "height": 1
          }
        }
      },
      "integration": {
        "type": "radarr",
        "properties": [
          {
            "field": "apiKey",
            "type": "private",
            "value": "627c442f302045e18844e31508825832"
          }
        ]
      }
    },
    {
      "id": "c6d1f214-5545-4279-aedb-f059dda70ee8",
      "name": "Kanban",
      "url": "https://kanban.virtual.lontiotlabs.au",
      "appearance": {
        "iconUrl": "https://www.dumbware.io/software/DumbKan/dumbkan.svg",
        "appNameStatus": "normal",
        "positionAppName": "column",
        "lineClampAppName": 1,
        "appNameFontSize": 16
      },
      "network": {
        "enabledStatusChecker": true,
        "statusCodes": [
          "200",
          "301",
          "302",
          "304",
          "307",
          "308"
        ]
      },
      "behaviour": {
        "isOpeningNewTab": true,
        "externalUrl": "https://kanban.virtual.lontiotlabs.au"
      },
      "area": {
        "type": "sidebar",
        "properties": {
          "location": "right"
        }
      },
      "shape": {
        "lg": {
          "location": {
            "x": 0,
            "y": 7
          },
          "size": {
            "width": 1,
            "height": 1
          }
        }
      },
      "integration": {
        "type": null,
        "properties": []
      }
    }
  ],
  "widgets": [
    {
      "id": "971aa859-8570-49a1-8d34-dd5c7b3638d1",
      "type": "date",
      "properties": {
        "display24HourFormat": true
      },
      "area": {
        "type": "wrapper",
        "properties": {
          "id": "default"
        }
      },
      "shape": {
        "sm": {
          "location": {
            "x": 0,
            "y": 1
          },
          "size": {
            "width": 2,
            "height": 1
          }
        },
        "md": {
          "location": {
            "x": 4,
            "y": 0
          },
          "size": {
            "width": 2,
            "height": 1
          }
        },
        "lg": {
          "location": {
            "x": 0,
            "y": 0
          },
          "size": {
            "width": 2,
            "height": 2
          }
        }
      }
    },
    {
      "id": "e3004052-6b83-480e-b458-56e8ccdca5f0",
      "type": "weather",
      "properties": {
        "displayInFahrenheit": false,
        "location": {
          "name": "Mill Park",
          "latitude": -37.66667,
          "longitude": 145.06667
        },
        "displayCityName": true,
        "displayWeekly": false,
        "forecastDays": 5
      },
      "area": {
        "type": "wrapper",
        "properties": {
          "id": "default"
        }
      },
      "shape": {
        "md": {
          "location": {
            "x": 0,
            "y": 0
          },
          "size": {
            "width": 2,
            "height": 1
          }
        },
        "sm": {
          "location": {
            "x": 1,
            "y": 0
          },
          "size": {
            "width": 2,
            "height": 1
          }
        },
        "lg": {
          "location": {
            "x": 2,
            "y": 0
          },
          "size": {
            "width": 3,
            "height": 2
          }
        }
      }
    },
    {
      "id": "51f27e61-5927-4591-b4c1-61f4bc3d5ca9",
      "type": "calendar",
      "properties": {
        "useSonarrv4": false,
        "sundayStart": false,
        "radarrReleaseType": "inCinemas"
      },
      "area": {
        "type": "wrapper",
        "properties": {
          "id": "default"
        }
      },
      "shape": {
        "sm": {
          "location": {
            "x": 0,
            "y": 0
          },
          "size": {
            "width": 2,
            "height": 2
          }
        },
        "md": {
          "location": {
            "x": 0,
            "y": 0
          },
          "size": {
            "width": 2,
            "height": 2
          }
        },
        "lg": {
          "location": {
            "x": 0,
            "y": 2
          },
          "size": {
            "width": 5,
            "height": 4
          }
        }
      }
    },
    {
      "id": "eda06754-8ef4-42ec-bdd3-72f05cd3d476",
      "type": "torrents-status",
      "properties": {
        "displayCompletedTorrents": true,
        "displayStaleTorrents": true,
        "labelFilterIsWhitelist": true,
        "labelFilter": [],
        "displayActiveTorrents": true,
        "speedLimitOfActiveTorrents": 10,
        "displayRatioWithFilter": true
      },
      "area": {
        "type": "wrapper",
        "properties": {
          "id": "default"
        }
      },
      "shape": {
        "sm": {
          "location": {
            "x": 0,
            "y": 0
          },
          "size": {
            "width": 2,
            "height": 2
          }
        },
        "md": {
          "location": {
            "x": 0,
            "y": 0
          },
          "size": {
            "width": 2,
            "height": 2
          }
        },
        "lg": {
          "location": {
            "x": 5,
            "y": 3
          },
          "size": {
            "width": 5,
            "height": 2
          }
        }
      }
    },
    {
      "id": "26221dc7-af16-44d0-9b14-170f86efceb3",
      "type": "dlspeed",
      "properties": {},
      "area": {
        "type": "wrapper",
        "properties": {
          "id": "default"
        }
      },
      "shape": {
        "sm": {
          "location": {
            "x": 0,
            "y": 0
          },
          "size": {
            "width": 2,
            "height": 2
          }
        },
        "md": {
          "location": {
            "x": 0,
            "y": 0
          },
          "size": {
            "width": 2,
            "height": 2
          }
        },
        "lg": {
          "location": {
            "x": 0,
            "y": 6
          },
          "size": {
            "width": 4,
            "height": 2
          }
        }
      }
    }
  ],
  "settings": {
    "common": {
      "searchEngine": {
        "type": "google",
        "properties": {}
      }
    },
    "customization": {
      "layout": {
        "enabledLeftSidebar": false,
        "enabledRightSidebar": true,
        "enabledDocker": true,
        "enabledPing": false,
        "enabledSearchbar": true
      },
      "pageTitle": "",
      "logoImageUrl": "/imgs/logo/logo.png",
      "faviconUrl": "/imgs/favicon/favicon-squared.png",
      "backgroundImageUrl": "",
      "customCss": "",
      "colors": {
        "primary": "red",
        "secondary": "yellow",
        "shade": 7
      },
      "appOpacity": 100,
      "gridstack": {
        "columnCountSmall": 3,
        "columnCountMedium": 6,
        "columnCountLarge": 12
      },
      "metaTitle": "",
      "backgroundImageAttachment": "fixed",
      "backgroundImageRepeat": "no-repeat",
      "backgroundImageSize": "cover"
    },
    "access": {
      "allowGuests": true
    }
  }
}